{
  "connectedSets": [
    {
      "points": [
        {
          "connectedLines": [],
          "x": 0.2377387575149874,
          "y": 0.7591311949656321
        },
        {
          "connectedLines": [],
          "x": 0.48415385983938114,
          "y": 0.6401568120640881
        },
        {
          "connectedLines": [],
          "x": 0.6753461618193309,
          "y": 0.405375451675099
        },
        {
          "connectedLines": [],
          "x": 0.6134263349575122,
          "y": 0.4513862782582067
        },
        {
          "connectedLines": [],
          "x": 0.48985543998799397,
          "y": 0.45956672792858305
        },
        {
          "connectedLines": [],
          "x": 0.41345705049180004,
          "y": 0.36582595549828206
        },
        {
          "connectedLines": [],
          "x": 0.4702971919762145,
          "y": 0.24534228883965162
        },
        {
          "connectedLines": [],
          "x": 0.5754275353517113,
          "y": 0.2215380120541725
        },
        {
          "connectedLines": [],
          "x": 0.6834580471990862,
          "y": 0.27904164432450057
        },
        {
          "connectedLines": [],
          "x": 0.6880391393599806,
          "y": 0.32568986362558944
        },
        {
          "connectedLines": [],
          "x": 0.6823322474783231,
          "y": 0.3562522436071902
        }
      ]
    }
  ]
}