{
  "connectedSets": [
    {
      "points": [
        {
          "connectedLines": [],
          "x": 0.487793785281649,
          "y": 0.7179714031880399
        },
        {
          "connectedLines": [],
          "x": 0.6273806285574149,
          "y": 0.6397485153921175
        },
        {
          "connectedLines": [],
          "x": 0.6762777704241818,
          "y": 0.32293160347258865
        },
        {
          "connectedLines": [],
          "x": 0.6039551491750392,
          "y": 0.26393624307148444
        },
        {
          "connectedLines": [],
          "x": 0.5659608895963055,
          "y": 0.1792284302844191
        },
        {
          "connectedLines": [],
          "x": 0.34207336078804107,
          "y": 0.15004723522122526
        },
        {
          "connectedLines": [],
          "x": 0.19600472302762906,
          "y": 0.32398127685486805
        },
        {
          "connectedLines": [],
          "x": 0.2005126652981525,
          "y": 0.4408788624125392
        },
        {
          "connectedLines": [],
          "x": 0.32399740986717473,
          "y": 0.48961502588863726
        },
        {
          "connectedLines": [],
          "x": 0.4671907676418073,
          "y": 0.39929043952140136
        },
        {
          "connectedLines": [],
          "x": 0.6109893063077717,
          "y": 0.34298826347180417
        }
      ]
    }
  ]
}