{
  "connectedSets": [
    {
      "points": [
        {
          "connectedLines": [],
          "x": 0.2937372428023868,
          "y": 0.36782026601327955
        },
        {
          "connectedLines": [],
          "x": 0.44614451025621765,
          "y": 0.17553352278119294
        },
        {
          "connectedLines": [],
          "x": 0.6274049767367467,
          "y": 0.3254947280445289
        },
        {
          "connectedLines": [],
          "x": 0.5279417153203239,
          "y": 0.4602916701481449
        },
        {
          "connectedLines": [],
          "x": 0.37637456754219145,
          "y": 0.47465508376503107
        },
        {
          "connectedLines": [],
          "x": 0.5369757324179415,
          "y": 0.5055887890453541
        },
        {
          "connectedLines": [],
          "x": 0.5858365004640833,
          "y": 0.6794957897034366
        },
        {
          "connectedLines": [],
          "x": 0.41661593331485336,
          "y": 0.780808849105916
        },
        {
          "connectedLines": [],
          "x": 0.32189494245669775,
          "y": 0.6048520921070325
        }
      ]
    }
  ]
}