{
  "connectedSets": [
    {
      "points": [
        {
          "connectedLines": [],
          "x": 0.5414939817329081,
          "y": 0.6494252493877279
        },
        {
          "connectedLines": [],
          "x": 0.4494958946197203,
          "y": 0.6437617412746631
        },
        {
          "connectedLines": [],
          "x": 0.3183978301965393,
          "y": 0.7266056074544737
        },
        {
          "connectedLines": [],
          "x": 0.475290664084674,
          "y": 0.4401746640908101
        },
        {
          "connectedLines": [],
          "x": 0.5275880593500786,
          "y": 0.2825744641813905
        },
        {
          "connectedLines": [],
          "x": 0.38375556548231515,
          "y": 0.1727299429419692
        },
        {
          "connectedLines": [],
          "x": 0.2659500528290087,
          "y": 0.28973016124681744
        }
      ]
    }
  ]
}