{
  "connectedSets": [
    {
      "points": [
        {
          "connectedLines": [],
          "x": 0.6918978539099864,
          "y": 0.3374876672539223
        },
        {
          "connectedLines": [],
          "x": 0.59045136146452,
          "y": 0.13342580278301605
        },
        {
          "connectedLines": [],
          "x": 0.40802698921628155,
          "y": 0.2540893486371118
        }
      ]
    },
    {
      "points": [
        {
          "connectedLines": [],
          "x": 0.6679712382280666,
          "y": 0.6609767392763533
        },
        {
          "connectedLines": [],
          "x": 0.43530704039607154,
          "y": 0.6412681992289752
        },
        {
          "connectedLines": [],
          "x": 0.37450253479458573,
          "y": 0.6557077456841535
        },
        {
          "connectedLines": [],
          "x": 0.5231338515802826,
          "y": 0.5202412454847618
        },
        {
          "connectedLines": [],
          "x": 0.7235679799745185,
          "y": 0.30483657656850766
        }
      ]
    }
  ]
}