{
  "connectedSets": [
    {
      "points": [
        {
          "connectedLines": [],
          "x": 0.5551578777112024,
          "y": 0.715386996941071
        },
        {
          "connectedLines": [],
          "x": 0.3147207858793228,
          "y": 0.7835525102369437
        },
        {
          "connectedLines": [],
          "x": 0.2838505415140218,
          "y": 0.788359088046399
        },
        {
          "connectedLines": [],
          "x": 0.3566759597644481,
          "y": 0.7752958347266625
        },
        {
          "connectedLines": [],
          "x": 0.5958905629174197,
          "y": 0.37391142220194384
        },
        {
          "connectedLines": [],
          "x": 0.4444434621880148,
          "y": 0.2543220462606619
        },
        {
          "connectedLines": [],
          "x": 0.3119101413725987,
          "y": 0.38440714126175163
        }
      ]
    }
  ]
}