{
  "connectedSets": [
    {
      "points": [
        {
          "connectedLines": [],
          "x": 0.20708709987272267,
          "y": 0.3550264733166763
        },
        {
          "connectedLines": [],
          "x": 0.34637884306796485,
          "y": 0.17315338252317955
        },
        {
          "connectedLines": [],
          "x": 0.5015742072071425,
          "y": 0.264602118905981
        },
        {
          "connectedLines": [],
          "x": 0.5056648700201486,
          "y": 0.4775647202361275
        },
        {
          "connectedLines": [],
          "x": 0.3294997286766802,
          "y": 0.670704018814462
        },
        {
          "connectedLines": [],
          "x": 0.42303156992931856,
          "y": 0.6655206186003852
        },
        {
          "connectedLines": [],
          "x": 0.6125083282214504,
          "y": 0.596172433365641
        }
      ]
    }
  ]
}