{
  "connectedSets": [
    {
      "points": [
        {
          "connectedLines": [],
          "x": 0.5729981103206707,
          "y": 0.5811014230515946
        },
        {
          "connectedLines": [],
          "x": 0.49190463840859416,
          "y": 0.6538207000560163
        },
        {
          "connectedLines": [],
          "x": 0.3525836280218139,
          "y": 0.7241814945634473
        },
        {
          "connectedLines": [],
          "x": 0.26008108238603633,
          "y": 0.8045322356978258
        },
        {
          "connectedLines": [],
          "x": 0.27336056029685146,
          "y": 0.8471897751775935
        },
        {
          "connectedLines": [],
          "x": 0.47703114857928763,
          "y": 0.5740257222122336
        },
        {
          "connectedLines": [],
          "x": 0.5288713287546682,
          "y": 0.25583383926075093
        },
        {
          "connectedLines": [],
          "x": 0.4130989616948986,
          "y": 0.19154523900985712
        },
        {
          "connectedLines": [],
          "x": 0.21100960468290522,
          "y": 0.301909643945256
        }
      ]
    }
  ]
}