{
  "connectedSets": [
    {
      "points": [
        {
          "connectedLines": [],
          "x": 0.6158296778059391,
          "y": 0.5657859478676374
        },
        {
          "connectedLines": [],
          "x": 0.5148993438698604,
          "y": 0.6079007632847322
        },
        {
          "connectedLines": [],
          "x": 0.39676543424699984,
          "y": 0.6834696847016651
        },
        {
          "connectedLines": [],
          "x": 0.4461232232418043,
          "y": 0.4556908231345211
        },
        {
          "connectedLines": [],
          "x": 0.5907711445013958,
          "y": 0.2555352482320003
        },
        {
          "connectedLines": [],
          "x": 0.4348008853056387,
          "y": 0.13990101737496352
        },
        {
          "connectedLines": [],
          "x": 0.25892151655573614,
          "y": 0.24672977325397696
        },
        {
          "connectedLines": [],
          "x": 0.4273330879881114,
          "y": 0.17752989841090325
        },
        {
          "connectedLines": [],
          "x": 0.6005045278269736,
          "y": 0.24236289093612529
        }
      ]
    }
  ]
}