{
  "connectedSets": [
    {
      "points": [
        {
          "connectedLines": [],
          "x": 0.45418327013188925,
          "y": 0.19889706940126983
        },
        {
          "connectedLines": [],
          "x": 0.32503485147852457,
          "y": 0.509592065566563
        },
        {
          "connectedLines": [],
          "x": 0.48444961489332783,
          "y": 0.6822632126808682
        },
        {
          "connectedLines": [],
          "x": 0.6920997168659627,
          "y": 0.6669517936653597
        },
        {
          "connectedLines": [],
          "x": 0.7133511718505953,
          "y": 0.4525627344684112
        },
        {
          "connectedLines": [],
          "x": 0.642276980823897,
          "y": 0.43689097602848015
        },
        {
          "connectedLines": [],
          "x": 0.5857048720536078,
          "y": 0.5098573295260203
        }
      ]
    }
  ]
}