{
  "connectedSets": [
    {
      "points": [
        {
          "connectedLines": [],
          "x": 0.35022422187186775,
          "y": 0.6098933254752043
        },
        {
          "connectedLines": [],
          "x": 0.3924453603563616,
          "y": 0.431889266871662
        },
        {
          "connectedLines": [],
          "x": 0.6533621592835693,
          "y": 0.3115511378984047
        }
      ]
    },
    {
      "points": [
        {
          "connectedLines": [],
          "x": 0.42326616840999554,
          "y": 0.5396500904151744
        },
        {
          "connectedLines": [],
          "x": 0.5724742452919236,
          "y": 0.4600963442249545
        },
        {
          "connectedLines": [],
          "x": 0.6989898340281236,
          "y": 0.531354744508346
        },
        {
          "connectedLines": [],
          "x": 0.5293076416019142,
          "y": 0.6173344743163719
        },
        {
          "connectedLines": [],
          "x": 0.37553192114607126,
          "y": 0.5955065217337294
        }
      ]
    }
  ]
}