{
  "connectedSets": [
    {
      "points": [
        {
          "connectedLines": [],
          "x": 0.8446261925557317,
          "y": 0.7924477313712782
        },
        {
          "connectedLines": [],
          "x": 0.6285679580723771,
          "y": 0.7589678276695003
        },
        {
          "connectedLines": [],
          "x": 0.4107885776002,
          "y": 0.7601781501064319
        },
        {
          "connectedLines": [],
          "x": 0.42740792317329473,
          "y": 0.4639978054104139
        },
        {
          "connectedLines": [],
          "x": 0.43502007958000366,
          "y": 0.15176452132823817
        },
        {
          "connectedLines": [],
          "x": 0.6021441297462559,
          "y": 0.11251607730050574
        },
        {
          "connectedLines": [],
          "x": 0.7572739667635024,
          "y": 0.10824974903398335
        },
        {
          "connectedLines": [],
          "x": 0.8106879732965524,
          "y": 0.43084586135066105
        },
        {
          "connectedLines": [],
          "x": 0.8135091643801782,
          "y": 0.7431450295108116
        }
      ]
    }
  ]
}