{
  "connectedSets": [
    {
      "points": [
        {
          "connectedLines": [],
          "x": 0.6119806244244776,
          "y": 0.7112872794365573
        },
        {
          "connectedLines": [],
          "x": 0.4885067231009176,
          "y": 0.40871570757531317
        },
        {
          "connectedLines": [],
          "x": 0.2756798445975966,
          "y": 0.12325923998053344
        },
        {
          "connectedLines": [],
          "x": 0.41699871726892,
          "y": 0.18839433840386446
        },
        {
          "connectedLines": [],
          "x": 0.5950430223070065,
          "y": 0.24312825901230267
        },
        {
          "connectedLines": [],
          "x": 0.6201864709436192,
          "y": 0.4582547405399199
        },
        {
          "connectedLines": [],
          "x": 0.6574327889117758,
          "y": 0.6725356324259524
        }
      ]
    }
  ]
}