{
  "connectedSets": [
    {
      "points": [
        {
          "connectedLines": [],
          "x": 0.685116227387936,
          "y": 0.2581696329083219
        },
        {
          "connectedLines": [],
          "x": 0.5295495653905635,
          "y": 0.2458593204694724
        },
        {
          "connectedLines": [],
          "x": 0.3469240546383887,
          "y": 0.2038427545383207
        },
        {
          "connectedLines": [],
          "x": 0.3168902041607311,
          "y": 0.5300721764867646
        },
        {
          "connectedLines": [],
          "x": 0.28019335359137243,
          "y": 0.8403292564904918
        },
        {
          "connectedLines": [],
          "x": 0.41542659776856516,
          "y": 0.8780603355475508
        },
        {
          "connectedLines": [],
          "x": 0.5397698434636733,
          "y": 0.8862270744017456
        }
      ]
    },
    {
      "points": [
        {
          "connectedLines": [],
          "x": 0.6269347722402585,
          "y": 0.9033730645169421
        },
        {
          "connectedLines": [],
          "x": 0.656572584427816,
          "y": 0.592578630964384
        },
        {
          "connectedLines": [],
          "x": 0.7714532003273696,
          "y": 0.337187826734469
        }
      ]
    }
  ]
}