{
  "connectedSets": [
    {
      "points": [
        {
          "connectedLines": [],
          "x": 0.4964091351252954,
          "y": 0.5598583967410995
        },
        {
          "connectedLines": [],
          "x": 0.5407478853922061,
          "y": 0.5516922551753264
        },
        {
          "connectedLines": [],
          "x": 0.5584649954696774,
          "y": 0.4929421280934508
        },
        {
          "connectedLines": [],
          "x": 0.4881055009418201,
          "y": 0.5547970632443447
        },
        {
          "connectedLines": [],
          "x": 0.40794706051559737,
          "y": 0.6289903833578896
        },
        {
          "connectedLines": [],
          "x": 0.4778034791483766,
          "y": 0.6612241272300442
        },
        {
          "connectedLines": [],
          "x": 0.5864635618683608,
          "y": 0.6522687418353476
        },
        {
          "connectedLines": [],
          "x": 0.4992564818357148,
          "y": 0.6794817817990897
        },
        {
          "connectedLines": [],
          "x": 0.3887452926127696,
          "y": 0.624217608220087
        },
        {
          "connectedLines": [],
          "x": 0.44616112231469396,
          "y": 0.5503940939338305
        },
        {
          "connectedLines": [],
          "x": 0.5578949854854761,
          "y": 0.4980546028300784
        },
        {
          "connectedLines": [],
          "x": 0.5399887828087535,
          "y": 0.40657506846738944
        },
        {
          "connectedLines": [],
          "x": 0.5246424503015187,
          "y": 0.34619467604917403
        }
      ]
    },
    {
      "points": [
        {
          "connectedLines": [],
          "x": 0.5044589356892109,
          "y": 0.3175193859094329
        },
        {
          "connectedLines": [],
          "x": 0.556816857461637,
          "y": 0.2842270863240123
        },
        {
          "connectedLines": [],
          "x": 0.6320619329008313,
          "y": 0.2962470292577688
        },
        {
          "connectedLines": [],
          "x": 0.6464548025602332,
          "y": 0.4000088177548577
        },
        {
          "connectedLines": [],
          "x": 0.5991540817098532,
          "y": 0.4982161465969422
        },
        {
          "connectedLines": [],
          "x": 0.5792494734205044,
          "y": 0.5400277028155037
        },
        {
          "connectedLines": [],
          "x": 0.5361789076687297,
          "y": 0.5567292343617805
        }
      ]
    }
  ]
}