{
  "connectedSets": [
    {
      "points": [
        {
          "connectedLines": [],
          "x": 0.5072359545435672,
          "y": 0.19118492955900118
        },
        {
          "connectedLines": [],
          "x": 0.4678042215246078,
          "y": 0.2762284155026756
        },
        {
          "connectedLines": [],
          "x": 0.4350017453757132,
          "y": 0.34711260704217606
        },
        {
          "connectedLines": [],
          "x": 0.3740463299232762,
          "y": 0.47125006888636195
        },
        {
          "connectedLines": [],
          "x": 0.4267983957009394,
          "y": 0.5959603602691989
        },
        {
          "connectedLines": [],
          "x": 0.41337497904481313,
          "y": 0.5037355852061465
        },
        {
          "connectedLines": [],
          "x": 0.4288786822247141,
          "y": 0.4113875834224711
        }
      ]
    },
    {
      "points": [
        {
          "connectedLines": [],
          "x": 0.46868396472429213,
          "y": 0.2260012484728952
        },
        {
          "connectedLines": [],
          "x": 0.3719785664680894,
          "y": 0.14701656532695206
        },
        {
          "connectedLines": [],
          "x": 0.27778869420996155,
          "y": 0.276897901568181
        },
        {
          "connectedLines": [],
          "x": 0.30923045617632783,
          "y": 0.3630845939675782
        },
        {
          "connectedLines": [],
          "x": 0.4095158641785194,
          "y": 0.4011148648309411
        },
        {
          "connectedLines": [],
          "x": 0.5612565714888539,
          "y": 0.40672002181432554
        },
        {
          "connectedLines": [],
          "x": 0.632203723172894,
          "y": 0.5040170800651302
        }
      ]
    },
    {
      "points": [
        {
          "connectedLines": [],
          "x": 0.676294010297056,
          "y": 0.49118482937166635
        },
        {
          "connectedLines": [],
          "x": 0.5756560120624097,
          "y": 0.6600973241940105
        },
        {
          "connectedLines": [],
          "x": 0.39330024971569477,
          "y": 0.6587782843059687
        }
      ]
    }
  ]
}