{
  "connectedSets": [
    {
      "points": [
        {
          "connectedLines": [],
          "x": 0.5400780508140827,
          "y": 0.4062643122635244
        },
        {
          "connectedLines": [],
          "x": 0.5694513616719264,
          "y": 0.4427765667807635
        },
        {
          "connectedLines": [],
          "x": 0.5754112318383299,
          "y": 0.4572202703432025
        },
        {
          "connectedLines": [],
          "x": 0.5913912850633019,
          "y": 0.6110446251490311
        },
        {
          "connectedLines": [],
          "x": 0.49894937702837955,
          "y": 0.7699298339326475
        }
      ]
    },
    {
      "points": [
        {
          "connectedLines": [],
          "x": 0.5925817918706013,
          "y": 0.44241310645043147
        },
        {
          "connectedLines": [],
          "x": 0.5809659178966131,
          "y": 0.4528635656183543
        },
        {
          "connectedLines": [],
          "x": 0.5807166920409851,
          "y": 0.4684865778590487
        },
        {
          "connectedLines": [],
          "x": 0.540768309366607,
          "y": 0.4454245536010759
        },
        {
          "connectedLines": [],
          "x": 0.5185002431733483,
          "y": 0.3874447046393088
        },
        {
          "connectedLines": [],
          "x": 0.5479019521818068,
          "y": 0.39803078560566785
        },
        {
          "connectedLines": [],
          "x": 0.6083844917042874,
          "y": 0.41349448100056413
        },
        {
          "connectedLines": [],
          "x": 0.5719279847607861,
          "y": 0.38479922534810884
        },
        {
          "connectedLines": [],
          "x": 0.5258223409002599,
          "y": 0.38793057537353365
        },
        {
          "connectedLines": [],
          "x": 0.5275449640448971,
          "y": 0.41866727288143907
        },
        {
          "connectedLines": [],
          "x": 0.5610003470488132,
          "y": 0.4510212284642529
        },
        {
          "connectedLines": [],
          "x": 0.48900027216346453,
          "y": 0.532277687434484
        },
        {
          "connectedLines": [],
          "x": 0.3946009151165742,
          "y": 0.6126180413692977
        },
        {
          "connectedLines": [],
          "x": 0.408207782113004,
          "y": 0.6893100865694022
        },
        {
          "connectedLines": [],
          "x": 0.4589024102215952,
          "y": 0.7852042445566754
        }
      ]
    }
  ]
}