{
  "connectedSets": [
    {
      "points": [
        {
          "connectedLines": [],
          "x": 0.23415281303180882,
          "y": 0.7130116239010342
        },
        {
          "connectedLines": [],
          "x": 0.5857245987102336,
          "y": 0.6138656685183608
        },
        {
          "connectedLines": [],
          "x": 0.6473131404081752,
          "y": 0.3965561602562426
        }
      ]
    },
    {
      "points": [
        {
          "connectedLines": [],
          "x": 0.3111670966445873,
          "y": 0.6446708783560321
        },
        {
          "connectedLines": [],
          "x": 0.34343167815550335,
          "y": 0.3847782403872385
        },
        {
          "connectedLines": [],
          "x": 0.642516716312234,
          "y": 0.3956210578824054
        }
      ]
    }
  ]
}