{
  "connectedSets": [
    {
      "points": [
        {
          "connectedLines": [],
          "x": 0.4597137567016977,
          "y": 0.6912947544394091
        },
        {
          "connectedLines": [],
          "x": 0.34613303552516833,
          "y": 0.4143228136293923
        },
        {
          "connectedLines": [],
          "x": 0.5823265850136262,
          "y": 0.2252284475675879
        },
        {
          "connectedLines": [],
          "x": 0.6639620627110389,
          "y": 0.5810652379440422
        },
        {
          "connectedLines": [],
          "x": 0.5391101016440385,
          "y": 0.7428182751532761
        },
        {
          "connectedLines": [],
          "x": 0.6492924524892438,
          "y": 0.5839501164964722
        },
        {
          "connectedLines": [],
          "x": 0.6010852271462586,
          "y": 0.24745709032641983
        }
      ]
    }
  ]
}