{
  "connectedSets": [
    {
      "points": [
        {
          "connectedLines": [],
          "x": 0.2892117910213214,
          "y": 0.6385353518803961
        },
        {
          "connectedLines": [],
          "x": 0.5057647474434427,
          "y": 0.2796860212295726
        },
        {
          "connectedLines": [],
          "x": 0.7100403626758695,
          "y": 0.32942452186646615
        },
        {
          "connectedLines": [],
          "x": 0.6813189262437659,
          "y": 0.6501740864014268
        },
        {
          "connectedLines": [],
          "x": 0.30527412664841624,
          "y": 0.6173991164557143
        },
        {
          "connectedLines": [],
          "x": 0.6865142826946673,
          "y": 0.6344112626591503
        },
        {
          "connectedLines": [],
          "x": 0.7799903404130413,
          "y": 0.3667781512531594
        }
      ]
    }
  ]
}