{
  "connectedSets": [
    {
      "points": [
        {
          "connectedLines": [],
          "x": 0.7303982028257678,
          "y": 0.683031384968378
        },
        {
          "connectedLines": [],
          "x": 0.6835961077638977,
          "y": 0.682152798796345
        },
        {
          "connectedLines": [],
          "x": 0.6063018457784524,
          "y": 0.6933921990490872
        },
        {
          "connectedLines": [],
          "x": 0.5738189060468106,
          "y": 0.4632943739539968
        },
        {
          "connectedLines": [],
          "x": 0.5006899380873779,
          "y": 0.2277542655896581
        }
      ]
    },
    {
      "points": [
        {
          "connectedLines": [],
          "x": 0.4126114440620621,
          "y": 0.7652498818584648
        },
        {
          "connectedLines": [],
          "x": 0.5119855526676125,
          "y": 0.7240095238144514
        },
        {
          "connectedLines": [],
          "x": 0.5899771415231257,
          "y": 0.7212982592661319
        },
        {
          "connectedLines": [],
          "x": 0.5419478048252444,
          "y": 0.47975121663155285
        },
        {
          "connectedLines": [],
          "x": 0.49327588629249414,
          "y": 0.2237247580683177
        },
        {
          "connectedLines": [],
          "x": 0.46093016332054804,
          "y": 0.2770152226893379
        },
        {
          "connectedLines": [],
          "x": 0.3973407883853308,
          "y": 0.32103210705192164
        },
        {
          "connectedLines": [],
          "x": 0.42121419183564446,
          "y": 0.3009560742665719
        },
        {
          "connectedLines": [],
          "x": 0.4837986858397315,
          "y": 0.19367002454294985
        }
      ]
    }
  ]
}