{
  "connectedSets": [
    {
      "points": [
        {
          "connectedLines": [],
          "x": 0.4411158869091168,
          "y": 0.24527879742506098
        },
        {
          "connectedLines": [],
          "x": 0.400668282439113,
          "y": 0.31210694878739986
        },
        {
          "connectedLines": [],
          "x": 0.3733471071406907,
          "y": 0.35017540259583474
        },
        {
          "connectedLines": [],
          "x": 0.38569550714857415,
          "y": 0.34060160281490637
        },
        {
          "connectedLines": [],
          "x": 0.436227319429442,
          "y": 0.28112572441541456
        },
        {
          "connectedLines": [],
          "x": 0.44046128830434095,
          "y": 0.5271097450734239
        },
        {
          "connectedLines": [],
          "x": 0.451851181584839,
          "y": 0.788540608098793
        },
        {
          "connectedLines": [],
          "x": 0.4582412059353277,
          "y": 0.8186806273433604
        },
        {
          "connectedLines": [],
          "x": 0.5015118934419812,
          "y": 0.8333295302948257
        },
        {
          "connectedLines": [],
          "x": 0.4878055897623375,
          "y": 0.8258276728953956
        },
        {
          "connectedLines": [],
          "x": 0.441262557366146,
          "y": 0.8231632208407658
        },
        {
          "connectedLines": [],
          "x": 0.3835317800991392,
          "y": 0.8467546219990885
        },
        {
          "connectedLines": [],
          "x": 0.3542222152237532,
          "y": 0.8380352139147097
        }
      ]
    }
  ]
}