{
  "connectedSets": [
    {
      "points": [
        {
          "connectedLines": [],
          "x": 0.616235215455159,
          "y": 0.699587425641905
        },
        {
          "connectedLines": [],
          "x": 0.5702875440867865,
          "y": 0.7072026210611586
        },
        {
          "connectedLines": [],
          "x": 0.49486352136706824,
          "y": 0.6875308037372744
        },
        {
          "connectedLines": [],
          "x": 0.433231065449559,
          "y": 0.6772840437826154
        },
        {
          "connectedLines": [],
          "x": 0.3420237059560804,
          "y": 0.6556068217485191
        },
        {
          "connectedLines": [],
          "x": 0.4015996121301139,
          "y": 0.6744513692791672
        },
        {
          "connectedLines": [],
          "x": 0.47354587215531346,
          "y": 0.7048532598673861
        },
        {
          "connectedLines": [],
          "x": 0.5382693121315651,
          "y": 0.4958994948607151
        },
        {
          "connectedLines": [],
          "x": 0.6149483198918794,
          "y": 0.2580884282258575
        },
        {
          "connectedLines": [],
          "x": 0.5063199663315018,
          "y": 0.27066158586280226
        },
        {
          "connectedLines": [],
          "x": 0.412669855124014,
          "y": 0.26940857406795543
        }
      ]
    }
  ]
}