{
  "connectedSets": [
    {
      "points": [
        {
          "connectedLines": [],
          "x": 0.5220017098421106,
          "y": 0.7897414403459284
        },
        {
          "connectedLines": [],
          "x": 0.5818436902740048,
          "y": 0.6626216127572169
        },
        {
          "connectedLines": [],
          "x": 0.6793664252283771,
          "y": 0.34977857028649395
        },
        {
          "connectedLines": [],
          "x": 0.49623656125258475,
          "y": 0.30990581614457946
        },
        {
          "connectedLines": [],
          "x": 0.3405234245992521,
          "y": 0.30912284155620146
        }
      ]
    },
    {
      "points": [
        {
          "connectedLines": [],
          "x": 0.7108333657189312,
          "y": 0.58035616977367
        },
        {
          "connectedLines": [],
          "x": 0.5749580618077593,
          "y": 0.6065744191045882
        },
        {
          "connectedLines": [],
          "x": 0.3997776658037483,
          "y": 0.5421190023251667
        }
      ]
    }
  ]
}