{
  "connectedSets": [
    {
      "points": [
        {
          "connectedLines": [],
          "x": 0.5316448843761437,
          "y": 0.7821953724020152
        },
        {
          "connectedLines": [],
          "x": 0.5566399332930584,
          "y": 0.6759419438473367
        },
        {
          "connectedLines": [],
          "x": 0.6387786988000064,
          "y": 0.34384674509791674
        },
        {
          "connectedLines": [],
          "x": 0.5163732494470227,
          "y": 0.36347246692623436
        },
        {
          "connectedLines": [],
          "x": 0.3486150834238383,
          "y": 0.32807098355461534
        },
        {
          "connectedLines": [],
          "x": 0.31347035625469194,
          "y": 0.3787660737893596
        },
        {
          "connectedLines": [],
          "x": 0.33593748837246284,
          "y": 0.4172084914086907
        }
      ]
    },
    {
      "points": [
        {
          "connectedLines": [],
          "x": 0.637069999207116,
          "y": 0.6558786454114827
        },
        {
          "connectedLines": [],
          "x": 0.6948002489670452,
          "y": 0.6748568679194482
        },
        {
          "connectedLines": [],
          "x": 0.7635575727559174,
          "y": 0.614861352904774
        }
      ]
    }
  ]
}