{
  "connectedSets": [
    {
      "points": [
        {
          "connectedLines": [],
          "x": 0.654766072899156,
          "y": 0.19454622496077256
        },
        {
          "connectedLines": [],
          "x": 0.5671384295089822,
          "y": 0.5105455284057211
        },
        {
          "connectedLines": [],
          "x": 0.570608728468601,
          "y": 0.6634900276014377
        },
        {
          "connectedLines": [],
          "x": 0.5646074064979028,
          "y": 0.5391739675757705
        },
        {
          "connectedLines": [],
          "x": 0.6233434860780003,
          "y": 0.21876794355651827
        },
        {
          "connectedLines": [],
          "x": 0.5140809371867925,
          "y": 0.21768411198099546
        },
        {
          "connectedLines": [],
          "x": 0.3587252872460939,
          "y": 0.2250379358091208
        }
      ]
    }
  ]
}