{
  "connectedSets": [
    {
      "points": [
        {
          "connectedLines": [],
          "x": 0.36869240501219913,
          "y": 0.3624114129325842
        },
        {
          "connectedLines": [],
          "x": 0.360787373891002,
          "y": 0.3489336123711831
        },
        {
          "connectedLines": [],
          "x": 0.34480664597893285,
          "y": 0.27248377378838107
        },
        {
          "connectedLines": [],
          "x": 0.4668444130227349,
          "y": 0.24775021762022745
        },
        {
          "connectedLines": [],
          "x": 0.6230406325779426,
          "y": 0.24828362058161751
        },
        {
          "connectedLines": [],
          "x": 0.543003363729359,
          "y": 0.5174266955780286
        },
        {
          "connectedLines": [],
          "x": 0.5917843948630669,
          "y": 0.6593663010131444
        },
        {
          "connectedLines": [],
          "x": 0.5540212040501358,
          "y": 0.5571085639238246
        },
        {
          "connectedLines": [],
          "x": 0.6216284830585755,
          "y": 0.3030534676620123
        }
      ]
    }
  ]
}