{
  "connectedSets": [
    {
      "points": [
        {
          "connectedLines": [],
          "x": 0.2763515943253119,
          "y": 0.3020467834872108
        },
        {
          "connectedLines": [],
          "x": 0.4624860650536574,
          "y": 0.2821663478414826
        },
        {
          "connectedLines": [],
          "x": 0.6340765772206775,
          "y": 0.2891844606946301
        },
        {
          "connectedLines": [],
          "x": 0.41024766083778336,
          "y": 0.5688022816471947
        },
        {
          "connectedLines": [],
          "x": 0.41996354630307137,
          "y": 0.7296273005449975
        },
        {
          "connectedLines": [],
          "x": 0.4184017252573698,
          "y": 0.6221580109682086
        },
        {
          "connectedLines": [],
          "x": 0.6555695426272511,
          "y": 0.29971846758607695
        }
      ]
    },
    {
      "points": [
        {
          "connectedLines": [],
          "x": 0.7564192819021636,
          "y": 0.45421728106976894
        },
        {
          "connectedLines": [],
          "x": 0.7127177194457935,
          "y": 0.5189333931507598
        },
        {
          "connectedLines": [],
          "x": 0.644823673169558,
          "y": 0.604595491400239
        }
      ]
    }
  ]
}