{
  "connectedSets": [
    {
      "points": [
        {
          "connectedLines": [],
          "x": 0.40365459438813633,
          "y": 0.44287156516018644
        },
        {
          "connectedLines": [],
          "x": 0.38405378965461523,
          "y": 0.3835274767675907
        },
        {
          "connectedLines": [],
          "x": 0.3662172342538971,
          "y": 0.3236268014304315
        },
        {
          "connectedLines": [],
          "x": 0.5191237359611873,
          "y": 0.292705231199145
        },
        {
          "connectedLines": [],
          "x": 0.6737701808800989,
          "y": 0.2734909600723332
        },
        {
          "connectedLines": [],
          "x": 0.5166895825878912,
          "y": 0.487610711643637
        },
        {
          "connectedLines": [],
          "x": 0.47647705492853093,
          "y": 0.6035422743087927
        },
        {
          "connectedLines": [],
          "x": 0.5187551965698197,
          "y": 0.5199678579367418
        },
        {
          "connectedLines": [],
          "x": 0.7069666742066951,
          "y": 0.29504098758677283
        },
        {
          "connectedLines": [],
          "x": 0.5544053832051534,
          "y": 0.3281075542119037
        },
        {
          "connectedLines": [],
          "x": 0.390351472007326,
          "y": 0.28584794819605897
        }
      ]
    }
  ]
}