{
  "connectedSets": [
    {
      "points": [
        {
          "connectedLines": [],
          "x": 0.2605832355020727,
          "y": 0.3299409831697222
        },
        {
          "connectedLines": [],
          "x": 0.40076767214926884,
          "y": 0.3400394977117255
        },
        {
          "connectedLines": [],
          "x": 0.5562286710311026,
          "y": 0.35530236727799747
        },
        {
          "connectedLines": [],
          "x": 0.34572722493419256,
          "y": 0.6203983576431171
        },
        {
          "connectedLines": [],
          "x": 0.4291579540278808,
          "y": 0.8366476079327984
        }
      ]
    }
  ]
}