{
  "connectedSets": [
    {
      "points": [
        {
          "connectedLines": [],
          "x": 0.6136393573314579,
          "y": 0.6367800633913341
        },
        {
          "connectedLines": [],
          "x": 0.5059069435934105,
          "y": 0.6544575477564877
        },
        {
          "connectedLines": [],
          "x": 0.3907969557541067,
          "y": 0.7027935122064047
        },
        {
          "connectedLines": [],
          "x": 0.43015227979707565,
          "y": 0.5841911522852197
        },
        {
          "connectedLines": [],
          "x": 0.6299564442875347,
          "y": 0.25240206006002824
        },
        {
          "connectedLines": [],
          "x": 0.4629364961780152,
          "y": 0.1647933939443076
        },
        {
          "connectedLines": [],
          "x": 0.30749449458365036,
          "y": 0.3115056924812198
        }
      ]
    }
  ]
}