{
  "connectedSets": [
    {
      "points": [
        {
          "connectedLines": [],
          "x": 0.8958885340380992,
          "y": 0.634243800818566
        },
        {
          "connectedLines": [],
          "x": 0.6167786662699035,
          "y": 0.6142633269315668
        },
        {
          "connectedLines": [],
          "x": 0.3327810483470005,
          "y": 0.49120431144215926
        },
        {
          "connectedLines": [],
          "x": 0.5526771897288197,
          "y": 0.41601765291160664
        },
        {
          "connectedLines": [],
          "x": 0.7954238542598312,
          "y": 0.31989264708170845
        }
      ]
    },
    {
      "points": [
        {
          "connectedLines": [],
          "x": 0.8003469247030827,
          "y": 0.29338437887271634
        },
        {
          "connectedLines": [],
          "x": 0.5852308178280577,
          "y": 0.4098686411682671
        },
        {
          "connectedLines": [],
          "x": 0.3108274892740014,
          "y": 0.5076491675765228
        },
        {
          "connectedLines": [],
          "x": 0.5721838637453301,
          "y": 0.593407191840589
        },
        {
          "connectedLines": [],
          "x": 0.8910117254268947,
          "y": 0.6300511697391772
        }
      ]
    },
    {
      "points": [
        {
          "connectedLines": [],
          "x": 0.791696866959123,
          "y": 0.283820326001528
        },
        {
          "connectedLines": [],
          "x": 0.7389932714359573,
          "y": 0.47583639668715605
        },
        {
          "connectedLines": [],
          "x": 0.6759135051314505,
          "y": 0.6959512915454944
        }
      ]
    }
  ]
}