{
  "connectedSets": [
    {
      "points": [
        {
          "connectedLines": [],
          "x": 0.34086323452236844,
          "y": 0.46172393553517466
        },
        {
          "connectedLines": [],
          "x": 0.36322317242587504,
          "y": 0.3714560663723106
        },
        {
          "connectedLines": [],
          "x": 0.3438726231696889,
          "y": 0.31263878538947065
        }
      ]
    },
    {
      "points": [
        {
          "connectedLines": [],
          "x": 0.2695436650128562,
          "y": 0.6374431774318222
        },
        {
          "connectedLines": [],
          "x": 0.3781263041064537,
          "y": 0.6317021990134489
        },
        {
          "connectedLines": [],
          "x": 0.4946513136101126,
          "y": 0.5870005703331767
        },
        {
          "connectedLines": [],
          "x": 0.4489955858448778,
          "y": 0.5250169459273821
        },
        {
          "connectedLines": [],
          "x": 0.3390529336982351,
          "y": 0.4658457707391547
        }
      ]
    },
    {
      "points": [
        {
          "connectedLines": [],
          "x": 0.6424145046465212,
          "y": 0.25319611353350735
        },
        {
          "connectedLines": [],
          "x": 0.47172274805432635,
          "y": 0.2726820723115711
        },
        {
          "connectedLines": [],
          "x": 0.2912691895173837,
          "y": 0.32170050942735035
        }
      ]
    }
  ]
}