{
  "connectedSets": [
    {
      "points": [
        {
          "connectedLines": [],
          "x": 0.3683260012226303,
          "y": 0.3911165417916099
        },
        {
          "connectedLines": [],
          "x": 0.3747002054877038,
          "y": 0.3446908813301549
        },
        {
          "connectedLines": [],
          "x": 0.37434357429670373,
          "y": 0.2510912989441093
        },
        {
          "connectedLines": [],
          "x": 0.3904574800687293,
          "y": 0.31076165529093175
        },
        {
          "connectedLines": [],
          "x": 0.3480245867383565,
          "y": 0.39185974984230465
        },
        {
          "connectedLines": [],
          "x": 0.5502267717662688,
          "y": 0.3915154324951659
        },
        {
          "connectedLines": [],
          "x": 0.7145560310220751,
          "y": 0.4990426307908654
        },
        {
          "connectedLines": [],
          "x": 0.5786115709497303,
          "y": 0.6757553476997619
        },
        {
          "connectedLines": [],
          "x": 0.27693647881643507,
          "y": 0.6228472823966846
        }
      ]
    },
    {
      "points": [
        {
          "connectedLines": [],
          "x": 0.37509627726874856,
          "y": 0.2307792348251185
        },
        {
          "connectedLines": [],
          "x": 0.5603256732348791,
          "y": 0.2319267210786909
        },
        {
          "connectedLines": [],
          "x": 0.6862573264660923,
          "y": 0.17016244182384765
        }
      ]
    }
  ]
}