{
  "connectedSets": [
    {
      "points": [
        {
          "connectedLines": [],
          "x": 0.3927486819201482,
          "y": 0.4459018668993235
        },
        {
          "connectedLines": [],
          "x": 0.4066234574021448,
          "y": 0.3849965213109675
        },
        {
          "connectedLines": [],
          "x": 0.44224602875648356,
          "y": 0.29838304524408754
        }
      ]
    },
    {
      "points": [
        {
          "connectedLines": [],
          "x": 0.40563866005210697,
          "y": 0.26615357248520227
        },
        {
          "connectedLines": [],
          "x": 0.5471035223171131,
          "y": 0.36344423582416785
        },
        {
          "connectedLines": [],
          "x": 0.7146123906864262,
          "y": 0.4461100775505042
        },
        {
          "connectedLines": [],
          "x": 0.6026688525073685,
          "y": 0.36172393720140356
        },
        {
          "connectedLines": [],
          "x": 0.4410399167225109,
          "y": 0.3062810438576309
        },
        {
          "connectedLines": [],
          "x": 0.41108577438467764,
          "y": 0.3423105749409059
        },
        {
          "connectedLines": [],
          "x": 0.38977178873933976,
          "y": 0.49515410297068435
        }
      ]
    },
    {
      "points": [
        {
          "connectedLines": [],
          "x": 0.3773577042320816,
          "y": 0.4838395492279569
        },
        {
          "connectedLines": [],
          "x": 0.4693181092370809,
          "y": 0.4990808614078142
        },
        {
          "connectedLines": [],
          "x": 0.4937030838328876,
          "y": 0.5983226606591197
        },
        {
          "connectedLines": [],
          "x": 0.4646319607144247,
          "y": 0.6692365602167151
        },
        {
          "connectedLines": [],
          "x": 0.3636671461522743,
          "y": 0.6710764621607319
        }
      ]
    }
  ]
}