{
  "connectedSets": [
    {
      "points": [
        {
          "connectedLines": [],
          "x": 0.3475864832065421,
          "y": 0.6082882092698906
        },
        {
          "connectedLines": [],
          "x": 0.44341999966207823,
          "y": 0.6537382706700834
        },
        {
          "connectedLines": [],
          "x": 0.5266713638924784,
          "y": 0.6142764475556182
        },
        {
          "connectedLines": [],
          "x": 0.44372930246192405,
          "y": 0.5057147370787405
        },
        {
          "connectedLines": [],
          "x": 0.3227278718314542,
          "y": 0.47819103555091075
        },
        {
          "connectedLines": [],
          "x": 0.32957149141582254,
          "y": 0.3852119670617772
        },
        {
          "connectedLines": [],
          "x": 0.3683777233879648,
          "y": 0.31799734235655075
        },
        {
          "connectedLines": [],
          "x": 0.4614795989076205,
          "y": 0.3249243622745335
        },
        {
          "connectedLines": [],
          "x": 0.5950713828432493,
          "y": 0.2896818352124546
        }
      ]
    }
  ]
}