{
  "connectedSets": [
    {
      "points": [
        {
          "connectedLines": [],
          "x": 0.1570281362118733,
          "y": 0.6280208495142237
        },
        {
          "connectedLines": [],
          "x": 0.35415698640696175,
          "y": 0.3429968710819257
        },
        {
          "connectedLines": [],
          "x": 0.6557215320102762,
          "y": 0.3050620925905809
        }
      ]
    },
    {
      "points": [
        {
          "connectedLines": [],
          "x": 0.6857235535899704,
          "y": 0.39929275276649107
        },
        {
          "connectedLines": [],
          "x": 0.5330093450557339,
          "y": 0.6477047840947104
        },
        {
          "connectedLines": [],
          "x": 0.22075597291421245,
          "y": 0.7090487258806843
        }
      ]
    }
  ]
}