{
  "connectedSets": [
    {
      "points": [
        {
          "connectedLines": [],
          "x": 0.8388120423549353,
          "y": 0.8156352384864413
        },
        {
          "connectedLines": [],
          "x": 0.8106167561298926,
          "y": 0.5517904705175966
        },
        {
          "connectedLines": [],
          "x": 0.7895153342414287,
          "y": 0.25854389240890174
        },
        {
          "connectedLines": [],
          "x": 0.5475997611594321,
          "y": 0.2047362936729635
        },
        {
          "connectedLines": [],
          "x": 0.23116013364083152,
          "y": 0.27006797480204225
        },
        {
          "connectedLines": [],
          "x": 0.25623835547313456,
          "y": 0.5452042627696493
        },
        {
          "connectedLines": [],
          "x": 0.3029390164596101,
          "y": 0.8623889222842672
        },
        {
          "connectedLines": [],
          "x": 0.5315927902616926,
          "y": 0.8673055619625059
        },
        {
          "connectedLines": [],
          "x": 0.8216349978091517,
          "y": 0.8774890582636895
        }
      ]
    }
  ]
}